data_memory.v
module data_memory (clk, reset, MemWrite, MemRead, read_address, Write_data, MemData_out);
    input clk, reset, MemWrite, MemRead;
    input [31:0] read_address, Write_data;
    output [31:0] MemData_out;

    reg [31:0] D_memory[63:0];
    integer k;

always @(posedge clk or posedge reset)
    begin 
        if(reset)
            begin   
                for (k = 0; k<64; k = k + 1) begin
                    D_memory[k] <= 32'b00;
                end
                end
                else if (MemWrite) begin
                    D_memory[read_address[7:2]] <= Write_data;
                end
    end

assign MemData_out = (MemRead) ? D_memory[read_address[7:2]] : 32'b0;

endmodule

alu.v
module ALU_unit(A, B, Control_in, ALU_Result, zero);
    input [31:0] A, B;
    input [3:0] Control_in;
    output reg zero;
    output reg [31:0] ALU_Result;

always @(*)
    begin
        case (Control_in)
            4'b0000: ALU_Result = A & B;        
            4'b0001: ALU_Result = A | B;       
            4'b0010: ALU_Result = A + B;        
            4'b0110: ALU_Result = A - B;       
            default: ALU_Result = 32'b0;       
        endcase
        zero = (ALU_Result == 32'b0) ? 1'b1 : 1'b0;
    end 
endmodule

alu_control.v
module alu_control (op, func7, func3, control_out);
    input func7;
    input [2:0] func3;
    input [1:0] op;
    output reg [3:0] control_out;

always @(*)
    begin
        case(op)
            2'b00: control_out = 4'b0010;
            2'b01: control_out = 4'b0110;
            2'b10: begin
                case({func7, func3})
                    4'b0_000: control_out = 4'b0010;
                    4'b1_000: control_out = 4'b0110;
                    4'b0_111: control_out = 4'b0000;
                    4'b0_110: control_out = 4'b0001;
                    default:  control_out = 4'b0010;
                endcase
            end
            default: control_out = 4'b0010;
        endcase
    end

endmodule

immediate_generator.v
module immediate_generator(
    input [6:0] op,
    input [31:0] instr,
    output reg [31:0] imm_ex
);

always @(*)
    begin
        case(op)
            7'b0000011: imm_ex = {{20{instr[31]}}, instr[31:20]};
            7'b0010011: imm_ex = {{20{instr[31]}}, instr[31:20]};
            7'b0100011: imm_ex = {{20{instr[31]}}, instr[31:25], instr[11:7]};
            7'b1100011: imm_ex = {{20{instr[31]}}, instr[7], instr[30:25], instr[11:8], 1'b0};
            default:    imm_ex = 32'b0;
        endcase
    end
endmodule

register_file.v
module register_file (
    input clk, reset, regwrite,
    input [4:0] reg1, reg2, rd,
    input [31:0] write_data,
    output [31:0] rd1, rd2
);

reg [31:0] Registers [31:0];
integer k;

always @ (negedge clk or posedge reset)
    begin
        if (reset) begin
            for (k = 0; k<32; k = k + 1) begin
                Registers[k] <= 32'b00;
            end
        end
        else if (regwrite) begin
            Registers[rd] <= write_data;
        end
    end

assign rd1 = (reg1 == 5'b0) ? 32'b0 : Registers[reg1];
assign rd2 = (reg2 == 5'b0) ? 32'b0 : Registers[reg2];

endmodule

control_unit.v
module control_unit(instr, branch, MemRead, MemtoReg, MemWrite, ALUOp, ALUSrc, RegWrite);
    input [6:0] instr;
    output reg branch, MemRead, MemtoReg, MemWrite, ALUSrc, RegWrite;
    output reg [1:0] ALUOp;

always @(*)
    begin
        case(instr)
        7'b0110011: {ALUSrc, MemtoReg, RegWrite, MemRead, MemWrite, branch, ALUOp} = 8'b001000_10;
          7'b0010011: {ALUSrc, MemtoReg, RegWrite, MemRead, MemWrite, branch, ALUOp} = 8'b10100010;
        7'b0000011 : {ALUSrc, MemtoReg, RegWrite, MemRead, MemWrite, branch, ALUOp} = 8'hF0;
        7'b0100011: {ALUSrc, MemtoReg, RegWrite, MemRead, MemWrite, branch, ALUOp} = 8'b100010_00;
        7'b1100011: {ALUSrc, MemtoReg, RegWrite, MemRead, MemWrite, branch, ALUOp} = 8'b000001_01;
        default:    {ALUSrc, MemtoReg, RegWrite, MemRead, MemWrite, branch, ALUOp} = 8'b000000_00;
        endcase
    end

endmodule

instruction_memory.v
module instruction_memory(
    input [31:0] read_address,
    output [31:0] inst_out
);

reg [31:0] i_mem [63:0];

initial begin
        $readmemh("programa.mem", i_mem);
end

assign inst_out = i_mem[read_address[7:2]];

endmodule

top.v
module top (clk, reset);
    input clk, reset;

    wire        PCSrc;
    wire        load_use;
    wire        PCWrite, IFID_Write;

    reg  [31:0] PC;
    wire [31:0] instr_IF, pc_plus4_IF, pc_next, pc_branch_EX;

    reg [31:0] IFID_instr, IFID_pc;

    wire [6:0] opcode_ID;
    wire [4:0] rs1_ID, rs2_ID, rd_ID;
    wire [2:0] func3_ID;
    wire       func7_ID;
    wire        branch_ID, MemRead_ID, MemtoReg_ID, MemWrite_ID, ALUSrc_ID, RegWrite_ID;
    wire [1:0]  ALUOp_ID;
    wire [31:0] rd1_ID, rd2_ID, imm_ID;

    reg        IDEX_branch, IDEX_MemRead, IDEX_MemtoReg, IDEX_MemWrite, IDEX_ALUSrc, IDEX_RegWrite;
    reg [1:0]  IDEX_ALUOp;
    reg [31:0] IDEX_pc, IDEX_rd1, IDEX_rd2, IDEX_imm;
    reg [4:0]  IDEX_rs1, IDEX_rs2, IDEX_rd;
    reg [2:0]  IDEX_func3;
    reg        IDEX_func7;

    wire [3:0]  alu_ctrl_EX;
    wire [31:0] alu_result_EX, alu_in_B;
    wire        zero_EX;
    wire [1:0]  forwardA, forwardB;
    reg  [31:0] alu_in_A, forwardB_val;

    reg        EXMEM_MemRead, EXMEM_MemtoReg, EXMEM_MemWrite, EXMEM_RegWrite;
    reg [31:0] EXMEM_alu_result, EXMEM_store_data;
    reg [4:0]  EXMEM_rd;

    wire [31:0] mem_out_MEM;

    reg        MEMWB_MemtoReg, MEMWB_RegWrite;
    reg [31:0] MEMWB_mem_out, MEMWB_alu_result;
    reg [4:0]  MEMWB_rd;

    wire [31:0] write_data_WB;

    wire [31:0] pc_plus4_old;
    wire [31:0] alu_result_unused;
    wire        branch_taken;

    assign pc_plus4_IF = PC + 4;
    assign pc_plus4_old = PC + 4;
    assign branch_taken = PCSrc;
    assign pc_next = PCSrc ? pc_branch_EX : pc_plus4_IF;

    instruction_memory inst_memory(.read_address(PC), .inst_out(instr_IF));

    always @(posedge clk or posedge reset) begin
        if (reset == 1'b1)
            PC <= 0;
        else if (PCWrite == 1'b1)
            PC <= pc_next;
    end

    always @(posedge clk or posedge reset) begin
        if (reset || PCSrc) begin
            IFID_instr <= 0;
            IFID_pc    <= 32'h00000000;
        end else if (IFID_Write) begin
            IFID_instr <= instr_IF;
            IFID_pc    <= PC;
        end
    end

    assign opcode_ID = IFID_instr[6:0];
    assign rs1_ID    = IFID_instr[19:15];
    assign rs2_ID    = IFID_instr[24:20];
    assign rd_ID     = IFID_instr[11:7];
    assign func3_ID  = IFID_instr[14:12];
    assign func7_ID  = IFID_instr[30];

    control_unit control_unit(.instr(opcode_ID), .branch(branch_ID), .MemRead(MemRead_ID),
        .MemtoReg(MemtoReg_ID), .MemWrite(MemWrite_ID), .ALUOp(ALUOp_ID),
        .ALUSrc(ALUSrc_ID), .RegWrite(RegWrite_ID));

    register_file register_file(.clk(clk), .reset(reset), .regwrite(MEMWB_RegWrite),
        .reg1(rs1_ID), .reg2(rs2_ID), .rd(MEMWB_rd), .write_data(write_data_WB),
        .rd1(rd1_ID), .rd2(rd2_ID));

    immediate_generator immediate_generator(.op(opcode_ID), .instr(IFID_instr), .imm_ex(imm_ID));

    assign load_use = (IDEX_MemRead == 1'b1) && (IDEX_rd != 0) &&
                      ((IDEX_rd == rs1_ID) || (IDEX_rd == rs2_ID));
    assign PCWrite    = ~load_use;
    assign IFID_Write = ~load_use;

    always @(posedge clk or posedge reset) begin
        if (reset || load_use || PCSrc) begin
            IDEX_branch   <= 1'b0;
            IDEX_MemRead  <= 1'b0;
            IDEX_MemtoReg <= 1'b0;
            IDEX_MemWrite <= 1'b0;
            IDEX_ALUSrc   <= 1'b0;
            IDEX_RegWrite <= 1'b0;
            IDEX_ALUOp    <= 2'b0;
            IDEX_pc       <= 32'b0;
            IDEX_rd1      <= 32'b0;
            IDEX_rd2      <= 32'b0;
            IDEX_imm      <= 32'b0;
            IDEX_rs1      <= 5'b0;
            IDEX_rs2      <= 5'b0;
            IDEX_rd       <= 5'b0;
            IDEX_func3    <= 3'b0;
            IDEX_func7    <= 1'b0;
        end else begin
            IDEX_branch   <= branch_ID;
            IDEX_MemRead  <= MemRead_ID;
            IDEX_MemtoReg <= MemtoReg_ID;
            IDEX_MemWrite <= MemWrite_ID;
            IDEX_ALUSrc   <= ALUSrc_ID;
            IDEX_RegWrite <= RegWrite_ID;
            IDEX_ALUOp    <= ALUOp_ID;
            IDEX_pc       <= IFID_pc;
            IDEX_rd1      <= rd1_ID;
            IDEX_rd2      <= rd2_ID;
            IDEX_imm      <= imm_ID;
            IDEX_rs1      <= rs1_ID;
            IDEX_rs2      <= rs2_ID;
            IDEX_rd       <= rd_ID;
            IDEX_func3    <= func3_ID;
            IDEX_func7    <= func7_ID;
        end
    end

    alu_control alu_control(.op(IDEX_ALUOp), .func7(IDEX_func7), .func3(IDEX_func3),
        .control_out(alu_ctrl_EX));

    assign forwardA =
        (EXMEM_RegWrite && (EXMEM_rd != 5'b0) && (EXMEM_rd == IDEX_rs1)) ? 2'b10 :
        (MEMWB_RegWrite && (MEMWB_rd != 5'b0) && (MEMWB_rd == IDEX_rs1)) ? 2'b01 : 2'b00;
    assign forwardB =
        (EXMEM_RegWrite && (EXMEM_rd != 5'b0) && (EXMEM_rd == IDEX_rs2)) ? 2'b10 :
        (MEMWB_RegWrite && (MEMWB_rd != 5'b0) && (MEMWB_rd == IDEX_rs2)) ? 2'b01 : 2'b00;

    always @(*) begin
        case (forwardA)
            2'b10:   alu_in_A = EXMEM_alu_result;
            2'b01:   alu_in_A = write_data_WB;
            default: alu_in_A = IDEX_rd1;
        endcase
    end

    always @(*) begin
        case (forwardB)
            2'b10:   forwardB_val = EXMEM_alu_result;
            2'b01:   forwardB_val = write_data_WB;
            default: forwardB_val = IDEX_rd2;
        endcase
    end

    assign alu_in_B      = IDEX_ALUSrc ? IDEX_imm : forwardB_val;
    assign pc_branch_EX  = IDEX_pc + IDEX_imm;
    assign PCSrc         = IDEX_branch & zero_EX;

    ALU_unit alu(.A(alu_in_A), .B(alu_in_B), .Control_in(alu_ctrl_EX),
        .ALU_Result(alu_result_EX), .zero(zero_EX));

    always @(posedge clk or posedge reset) begin
        if (reset) begin
            EXMEM_MemRead    <= 0;
            EXMEM_MemtoReg   <= 1'b0;
            EXMEM_MemWrite   <= 1'b0;
            EXMEM_RegWrite   <= 1'b0;
            EXMEM_alu_result <= 32'd0;
            EXMEM_store_data <= 32'h00000000;
            EXMEM_rd         <= 0;
        end else begin
            EXMEM_MemRead    <= IDEX_MemRead;
            EXMEM_MemtoReg   <= IDEX_MemtoReg;
            EXMEM_MemWrite   <= IDEX_MemWrite;
            EXMEM_RegWrite   <= IDEX_RegWrite;
            EXMEM_alu_result <= alu_result_EX;
            EXMEM_store_data <= forwardB_val;
            EXMEM_rd         <= IDEX_rd;
        end
    end

    data_memory data_memory(.clk(clk), .reset(reset), .MemWrite(EXMEM_MemWrite),
        .MemRead(EXMEM_MemRead), .read_address(EXMEM_alu_result),
        .Write_data(EXMEM_store_data), .MemData_out(mem_out_MEM));

    always @(posedge clk or posedge reset) begin
        if (reset) begin
            MEMWB_MemtoReg   <= 1'b0;
            MEMWB_RegWrite   <= 1'b0;
            MEMWB_mem_out    <= 32'b0;
            MEMWB_alu_result <= 32'b0;
            MEMWB_rd         <= 5'b0;
        end else begin
            MEMWB_MemtoReg   <= EXMEM_MemtoReg;
            MEMWB_RegWrite   <= EXMEM_RegWrite;
            MEMWB_mem_out    <= mem_out_MEM;
            MEMWB_alu_result <= EXMEM_alu_result;
            MEMWB_rd         <= EXMEM_rd;
        end
    end

    assign write_data_WB = MEMWB_MemtoReg ? MEMWB_mem_out : MEMWB_alu_result;

endmodule

top_tb.v
module top_tb;
    reg clk;
    reg reset;

    top uut (.clk(clk), .reset(reset));

    always #5 clk = ~clk;

    initial begin
        $dumpfile("simulacion.vcd"); // Nombre del archivo que va a generar
        $dumpvars(0, top_tb);

        clk = 0;
        reset = 1;
        
        #10;
        reset = 0;
        
         #200;
        $finish;
    end

endmodule

simulacion.vcd
$date
	Sat Jun 13 20:29:44 2026
$end
$version
	Icarus Verilog
$end
$timescale
	1s
$end
$scope module top_tb $end
$var reg 1 ! clk $end
$var reg 1 " reset $end
$scope module uut $end
$var wire 1 # IFID_Write $end
$var wire 1 $ PCSrc $end
$var wire 1 % PCWrite $end
$var wire 1 & branch_taken $end
$var wire 1 ! clk $end
$var wire 1 ' load_use $end
$var wire 1 " reset $end
$var wire 1 ( zero_EX $end
$var wire 32 ) write_data_WB [31:0] $end
$var wire 5 * rs2_ID [4:0] $end
$var wire 5 + rs1_ID [4:0] $end
$var wire 5 , rd_ID [4:0] $end
$var wire 32 - rd2_ID [31:0] $end
$var wire 32 . rd1_ID [31:0] $end
$var wire 32 / pc_plus4_old [31:0] $end
$var wire 32 0 pc_plus4_IF [31:0] $end
$var wire 32 1 pc_next [31:0] $end
$var wire 32 2 pc_branch_EX [31:0] $end
$var wire 7 3 opcode_ID [6:0] $end
$var wire 32 4 mem_out_MEM [31:0] $end
$var wire 32 5 instr_IF [31:0] $end
$var wire 32 6 imm_ID [31:0] $end
$var wire 1 7 func7_ID $end
$var wire 3 8 func3_ID [2:0] $end
$var wire 2 9 forwardB [1:0] $end
$var wire 2 : forwardA [1:0] $end
$var wire 1 ; branch_ID $end
$var wire 32 < alu_result_EX [31:0] $end
$var wire 32 = alu_in_B [31:0] $end
$var wire 4 > alu_ctrl_EX [3:0] $end
$var wire 1 ? RegWrite_ID $end
$var wire 1 @ MemtoReg_ID $end
$var wire 1 A MemWrite_ID $end
$var wire 1 B MemRead_ID $end
$var wire 1 C ALUSrc_ID $end
$var wire 2 D ALUOp_ID [1:0] $end
$var reg 1 E EXMEM_MemRead $end
$var reg 1 F EXMEM_MemWrite $end
$var reg 1 G EXMEM_MemtoReg $end
$var reg 1 H EXMEM_RegWrite $end
$var reg 32 I EXMEM_alu_result [31:0] $end
$var reg 5 J EXMEM_rd [4:0] $end
$var reg 32 K EXMEM_store_data [31:0] $end
$var reg 2 L IDEX_ALUOp [1:0] $end
$var reg 1 M IDEX_ALUSrc $end
$var reg 1 N IDEX_MemRead $end
$var reg 1 O IDEX_MemWrite $end
$var reg 1 P IDEX_MemtoReg $end
$var reg 1 Q IDEX_RegWrite $end
$var reg 1 R IDEX_branch $end
$var reg 3 S IDEX_func3 [2:0] $end
$var reg 1 T IDEX_func7 $end
$var reg 32 U IDEX_imm [31:0] $end
$var reg 32 V IDEX_pc [31:0] $end
$var reg 5 W IDEX_rd [4:0] $end
$var reg 32 X IDEX_rd1 [31:0] $end
$var reg 32 Y IDEX_rd2 [31:0] $end
$var reg 5 Z IDEX_rs1 [4:0] $end
$var reg 5 [ IDEX_rs2 [4:0] $end
$var reg 32 \ IFID_instr [31:0] $end
$var reg 32 ] IFID_pc [31:0] $end
$var reg 1 ^ MEMWB_MemtoReg $end
$var reg 1 _ MEMWB_RegWrite $end
$var reg 32 ` MEMWB_alu_result [31:0] $end
$var reg 32 a MEMWB_mem_out [31:0] $end
$var reg 5 b MEMWB_rd [4:0] $end
$var reg 32 c PC [31:0] $end
$var reg 32 d alu_in_A [31:0] $end
$var reg 32 e forwardB_val [31:0] $end
$scope module alu $end
$var wire 32 f A [31:0] $end
$var wire 32 g B [31:0] $end
$var wire 4 h Control_in [3:0] $end
$var reg 32 i ALU_Result [31:0] $end
$var reg 1 ( zero $end
$upscope $end
$scope module alu_control $end
$var wire 3 j func3 [2:0] $end
$var wire 1 T func7 $end
$var wire 2 k op [1:0] $end
$var reg 4 l control_out [3:0] $end
$upscope $end
$scope module control_unit $end
$var wire 7 m instr [6:0] $end
$var reg 2 n ALUOp [1:0] $end
$var reg 1 C ALUSrc $end
$var reg 1 B MemRead $end
$var reg 1 A MemWrite $end
$var reg 1 @ MemtoReg $end
$var reg 1 ? RegWrite $end
$var reg 1 ; branch $end
$upscope $end
$scope module data_memory $end
$var wire 1 E MemRead $end
$var wire 1 F MemWrite $end
$var wire 32 o Write_data [31:0] $end
$var wire 1 ! clk $end
$var wire 32 p read_address [31:0] $end
$var wire 1 " reset $end
$var wire 32 q MemData_out [31:0] $end
$var integer 32 r k [31:0] $end
$upscope $end
$scope module immediate_generator $end
$var wire 32 s instr [31:0] $end
$var wire 7 t op [6:0] $end
$var reg 32 u imm_ex [31:0] $end
$upscope $end
$scope module inst_memory $end
$var wire 32 v inst_out [31:0] $end
$var wire 32 w read_address [31:0] $end
$upscope $end
$scope module register_file $end
$var wire 1 ! clk $end
$var wire 5 x rd [4:0] $end
$var wire 5 y reg1 [4:0] $end
$var wire 5 z reg2 [4:0] $end
$var wire 1 _ regwrite $end
$var wire 1 " reset $end
$var wire 32 { write_data [31:0] $end
$var wire 32 | rd2 [31:0] $end
$var wire 32 } rd1 [31:0] $end
$var integer 32 ~ k [31:0] $end
$upscope $end
$upscope $end
$upscope $end
$enddefinitions $end
$comment Show the parameter values. $end
$dumpall
$end
#0
$dumpvars
b100000 ~
b0 }
b0 |
b0 {
b0 z
b0 y
b0 x
b0 w
b1000000000000010010011 v
b0 u
b0 t
b0 s
b1000000 r
b0 q
b0 p
b0 o
b0 n
b0 m
b10 l
b0 k
b0 j
b0 i
b10 h
b0 g
b0 f
b0 e
b0 d
b0 c
b0 b
b0 a
b0 `
0_
0^
b0 ]
b0 \
b0 [
b0 Z
b0 Y
b0 X
b0 W
b0 V
b0 U
0T
b0 S
0R
0Q
0P
0O
0N
0M
b0 L
b0 K
b0 J
b0 I
0H
0G
0F
0E
b0 D
0C
0B
0A
0@
0?
b10 >
b0 =
b0 <
0;
b0 :
b0 9
b0 8
07
b0 6
b1000000000000010010011 5
b0 4
b0 3
b0 2
b100 1
b100 0
b100 /
b0 .
b0 -
b0 ,
b0 +
b0 *
b0 )
1(
0'
0&
1%
0$
1#
1"
0!
$end
#5
b1000000 r
1!
#10
0!
0"
#15
b1100000000000100010011 5
b1100000000000100010011 v
1C
1?
b10 D
b10 n
b10 6
b10 u
b1000 1
b10011 3
b10011 m
b10011 t
b10 *
b10 z
b1 ,
b1000 0
b1000 /
b100 c
b100 w
b1000000000000010010011 \
b1000000000000010010011 s
1!
#20
0!
#25
0(
b10 <
b10 i
b1000001000000100110011 5
b1000001000000100110011 v
b10 =
b10 g
b11 *
b11 z
b10 ,
b11 6
b11 u
b1100 1
b1 W
b10 [
b10 2
b10 U
b10 L
b10 k
1Q
1M
b100 ]
b1100000000000100010011 \
b1100000000000100010011 s
b1100 0
b1100 /
b1000 c
b1000 w
1!
#30
0!
#35
b1000001010111000100011 5
b1000001010111000100011 v
0C
b11 <
b11 i
b10000 1
b110011 3
b110011 m
b110011 t
b1 +
b1 y
b10 *
b10 z
b0 6
b0 u
b11 =
b11 g
b10000 0
b10000 /
b1100 c
b1100 w
b1000 ]
b1000001000000100110011 \
b1000001000000100110011 s
b10 W
b11 [
b11 U
b111 2
b100 V
b1 J
b10 I
b10 p
1H
1!
#40
0!
#45
b10 d
b10 f
b1 :
b11 e
b10 9
0(
b101 <
b101 i
1C
0?
1A
b0 D
b0 n
b11100 6
b11100 u
b1010000110000011 5
b1010000110000011 v
b10 )
b10 {
b11 =
b11 g
b100011 3
b100011 m
b100011 t
b11100 ,
b10 8
b10100 1
b1 b
b1 x
b10 `
1_
b10 J
b11 I
b11 p
b10 [
b1 Z
b0 U
b1000 2
b1000 V
0M
b1100 ]
b1000001010111000100011 \
b1000001010111000100011 s
b10100 0
b10100 /
b10000 c
b10000 w
1!
#50
b10 .
b10 }
0!
#55
b0 :
b1100001000010001100011 5
b1100001000010001100011 v
1@
1?
1B
0A
b11110 <
b11110 i
b11000 1
b11 3
b11 m
b11 t
b0 *
b0 z
b11 ,
b0 6
b0 u
b11100 =
b11100 g
b10 d
b10 f
b101 e
b11 )
b11 {
b11000 0
b11000 /
b10100 c
b10100 w
b10000 ]
b1010000110000011 \
b1010000110000011 s
b10 S
b10 j
b11100 W
b11100 U
b10 X
b101000 2
b1100 V
b0 L
b0 k
0Q
1M
1O
b11 K
b11 o
b101 I
b101 p
b10 b
b10 x
b11 `
1!
#60
0!
#65
0%
0#
1'
b0 9
b10 <
b10 i
0C
0@
0?
0B
1;
b1 D
b1 n
bx 5
bx v
b101 )
b101 {
b0 e
b0 =
b0 g
b1100011 3
b1100011 m
b1100011 t
b11 *
b11 z
b1000 ,
b0 8
b1000 6
b1000 u
b11100 1
b101 `
b11100 J
b101 K
b101 o
b11110 I
b11110 p
0H
1F
b11 W
b0 [
b0 U
b10000 2
b10000 V
1Q
0O
1P
1N
b10100 ]
b1100001000010001100011 \
b1100001000010001100011 s
b11100 0
b11100 /
b11000 c
b11000 w
1!
#70
0!
#75
1%
1#
0'
1(
b0 <
b0 i
b0 d
b0 f
b0 4
b0 q
b11110 )
b11110 {
b0 S
b0 j
b0 W
b0 Z
b0 X
b0 2
b0 V
0Q
0M
0P
0N
b11 J
b0 K
b0 o
b10 I
b10 p
1H
0F
1G
1E
b11100 b
b11100 x
b11110 `
0_
1!
#80
0!
#85
b1 9
0(
b10 <
b10 i
0;
b0 D
b0 n
bx .
bx }
bx -
bx |
b0 )
b0 {
b10 d
b10 f
b110 >
b110 h
b110 l
0&
0$
bx 3
bx m
bx t
bx +
bx y
bx *
bx z
bx ,
bx 8
x7
b0 6
b0 u
b100000 1
b11 b
b11 x
b10 `
1_
1^
b0 J
b0 I
b0 p
0H
0G
0E
b1000 W
b11 [
b1 Z
b1000 U
b10 X
b11100 2
b10100 V
b1 L
b1 k
1R
b11000 ]
bx \
bx s
b100000 0
b100000 /
b11100 c
b11100 w
1!
#90
0!
#95
bx =
bx g
bx e
b0 9
x(
bx <
bx i
b100100 1
b10 >
b10 h
b10 l
bx d
bx f
b100100 0
b100100 /
b100000 c
b100000 w
b11100 ]
xT
bx S
bx j
bx W
bx [
bx Z
b0 U
bx Y
bx X
b11000 2
b11000 V
b0 L
b0 k
0R
b1000 J
b10 I
b10 p
b0 b
b0 x
b0 `
0_
0^
1!
#100
0!
#105
b10 )
b10 {
b101000 1
b1000 b
b1000 x
b10 `
bx J
bx K
bx o
bx I
bx p
b11100 2
b11100 V
b100000 ]
b101000 0
b101000 /
b100100 c
b100100 w
1!
#110
0!
#115
b101100 1
bx )
bx {
b101100 0
b101100 /
b101000 c
b101000 w
b100100 ]
b100000 2
b100000 V
bx b
bx x
bx `
1!
#120
0!
#125
b110000 1
b100100 2
b100100 V
b101000 ]
b110000 0
b110000 /
b101100 c
b101100 w
1!
#130
0!
#135
b110100 1
b110100 0
b110100 /
b110000 c
b110000 w
b101100 ]
b101000 2
b101000 V
1!
#140
0!
#145
b111000 1
b101100 2
b101100 V
b110000 ]
b111000 0
b111000 /
b110100 c
b110100 w
1!
#150
0!
#155
b111100 1
b111100 0
b111100 /
b111000 c
b111000 w
b110100 ]
b110000 2
b110000 V
1!
#160
0!
#165
b1000000 1
b110100 2
b110100 V
b111000 ]
b1000000 0
b1000000 /
b111100 c
b111100 w
1!
#170
0!
#175
b1000100 1
b1000100 0
b1000100 /
b1000000 c
b1000000 w
b111100 ]
b111000 2
b111000 V
1!
#180
0!
#185
b1001000 1
b111100 2
b111100 V
b1000000 ]
b1001000 0
b1001000 /
b1000100 c
b1000100 w
1!
#190
0!
#195
b1001100 1
b1001100 0
b1001100 /
b1001000 c
b1001000 w
b1000100 ]
b1000000 2
b1000000 V
1!
#200
0!
#205
b1010000 1
b1000100 2
b1000100 V
b1001000 ]
b1010000 0
b1010000 /
b1001100 c
b1001100 w
1!
